CHANGELOG.txt
LICENCE.txt
MANIFEST.in
README.txt
setup.py
tweetdatalib4/__init__.py
tweetdatalib4.egg-info/PKG-INFO
tweetdatalib4.egg-info/SOURCES.txt
tweetdatalib4.egg-info/dependency_links.txt
tweetdatalib4.egg-info/top_level.txt